{
	"name": "Variable DFlow Columna Dinamica",
	"properties": {
		"activities": [
			{
				"name": "DFlow_Variables",
				"type": "ExecuteDataFlow",
				"dependsOn": [],
				"policy": {
					"timeout": "7.00:00:00",
					"retry": 0,
					"retryIntervalInSeconds": 30,
					"secureOutput": false,
					"secureInput": false
				},
				"userProperties": [],
				"typeProperties": {
					"dataflow": {
						"referenceName": "dataflowVariableColumnaDinamica",
						"type": "DataFlowReference",
						"parameters": {
							"Campo": {
								"value": "'@{variables('CampoFecha')}'",
								"type": "Expression"
							}
						},
						"datasetParameters": {
							"LecturaADL": {
								"Carpeta": {
									"value": "@pipeline().parameters.PCarpeta",
									"type": "Expression"
								},
								"Archivo": {
									"value": "@pipeline().parameters.PArchivo",
									"type": "Expression"
								}
							}
						}
					},
					"compute": {
						"coreCount": 8,
						"computeType": "General"
					}
				}
			},
			{
				"name": "Copy data1",
				"type": "Copy",
				"dependsOn": [
					{
						"activity": "DFlow_Variables",
						"dependencyConditions": [
							"Succeeded"
						]
					}
				],
				"policy": {
					"timeout": "7.00:00:00",
					"retry": 0,
					"retryIntervalInSeconds": 30,
					"secureOutput": false,
					"secureInput": false
				},
				"userProperties": [],
				"typeProperties": {
					"source": {
						"type": "SqlServerSource",
						"queryTimeout": "02:00:00"
					},
					"sink": {
						"type": "ParquetSink",
						"storeSettings": {
							"type": "AzureBlobFSWriteSettings"
						}
					},
					"enableStaging": false,
					"translator": {
						"type": "TabularTranslator",
						"typeConversion": true,
						"typeConversionSettings": {
							"allowDataTruncation": true,
							"treatBooleanAsNumber": false
						}
					}
				},
				"inputs": [
					{
						"referenceName": "SqlServerTableAdWorks",
						"type": "DatasetReference",
						"parameters": {
							"PEsquema": "Production",
							"PTabla": "ProductCategory"
						}
					}
				],
				"outputs": [
					{
						"referenceName": "LoadADL",
						"type": "DatasetReference",
						"parameters": {
							"Carpeta": "Parametros",
							"Archivo": "ProductCategory.Parquet"
						}
					}
				]
			}
		],
		"parameters": {
			"PCarpeta": {
				"type": "string",
				"defaultValue": "Parametros"
			},
			"PArchivo": {
				"type": "string",
				"defaultValue": "ProductCategory.Parquet"
			},
			"PFecha": {
				"type": "string",
				"defaultValue": "2008-04-30 00:00:00"
			}
		},
		"variables": {
			"VFecha": {
				"type": "String",
				"defaultValue": "@{pipeline().parameters.PFecha}"
			},
			"CampoFecha": {
				"type": "String",
				"defaultValue": "ProductCategoryID"
			}
		},
		"folder": {
			"name": "Migracion Banco W"
		},
		"annotations": []
	}
}