{
	"$schema": "http://schema.management.azure.com/schemas/2015-01-01/deploymentTemplate.json#",
	"contentVersion": "1.0.0.0",
	"parameters": {
		"factoryName": {
			"type": "string",
			"metadata": "Data Factory name",
			"defaultValue": "IntegrationsServices"
		}
	},
	"variables": {
		"factoryId": "[concat('Microsoft.DataFactory/factories/', parameters('factoryName'))]"
	},
	"resources": [
		{
			"name": "[concat(parameters('factoryName'), '/Variables')]",
			"type": "Microsoft.DataFactory/factories/pipelines",
			"apiVersion": "2018-06-01",
			"properties": {
				"activities": [
					{
						"name": "Until1",
						"description": "No se detiene hasta que encuentre el archivo, por eso hay que colocar una limitante de intentos",
						"type": "Until",
						"dependsOn": [],
						"userProperties": [],
						"typeProperties": {
							"expression": {
								"value": "@or(variables('FileExists'),greaterOrEquals(int(variables('IntCounter')),5))",
								"type": "Expression"
							},
							"activities": [
								{
									"name": "Get Metadata1",
									"type": "GetMetadata",
									"dependsOn": [],
									"policy": {
										"timeout": "7.00:00:00",
										"retry": 0,
										"retryIntervalInSeconds": 30,
										"secureOutput": false,
										"secureInput": false
									},
									"userProperties": [],
									"typeProperties": {
										"dataset": {
											"referenceName": "LoadADL",
											"type": "DatasetReference",
											"parameters": {
												"Carpeta": "Parametros",
												"Archivo": "roductCategory.Parquet"
											}
										},
										"fieldList": [
											"exists"
										],
										"storeSettings": {
											"type": "AzureBlobFSReadSettings",
											"recursive": true
										}
									}
								},
								{
									"name": "Set variable1",
									"type": "SetVariable",
									"dependsOn": [
										{
											"activity": "Get Metadata1",
											"dependencyConditions": [
												"Succeeded"
											]
										}
									],
									"userProperties": [],
									"typeProperties": {
										"variableName": "FileExists",
										"value": {
											"value": "@activity('Get Metadata1').output.exists",
											"type": "Expression"
										}
									}
								},
								{
									"name": "Set variable2",
									"type": "SetVariable",
									"dependsOn": [],
									"userProperties": [],
									"typeProperties": {
										"variableName": "IntTempCounter",
										"value": {
											"value": "@string(add(int(variables('IntCounter')),1))",
											"type": "Expression"
										}
									}
								},
								{
									"name": "Set variable3",
									"type": "SetVariable",
									"dependsOn": [
										{
											"activity": "Set variable2",
											"dependencyConditions": [
												"Succeeded"
											]
										}
									],
									"userProperties": [],
									"typeProperties": {
										"variableName": "IntCounter",
										"value": {
											"value": "@variables('IntTempCounter')",
											"type": "Expression"
										}
									}
								}
							],
							"timeout": "7.00:00:00"
						}
					}
				],
				"variables": {
					"FileExists": {
						"type": "Boolean"
					},
					"IntCounter": {
						"type": "String",
						"defaultValue": "0"
					},
					"IntTempCounter": {
						"type": "String",
						"defaultValue": "0"
					}
				},
				"folder": {
					"name": "Ejercicios"
				},
				"annotations": []
			},
			"dependsOn": []
		}
	]
}